tambur
