Metadata-Version: 1.0
Name: tambur
Version: 0.1.2.3
Summary: Tambur.io Client
Home-page: http://github.com/tamburio/python-tambur
Author: Andre Graf
Author-email: graf@tambur.io
License: UNKNOWN
Platform: UNKNOWN
Classifier: Intended Audience :: Developers
Classifier: License :: OSI Approved :: BSD License
Classifier: Operating System :: OS Independent
Classifier: Programming Language :: Python
Classifier: Topic :: Software Development :: Libraries :: Python Modules
